simcombustion/__init__.py
simcombustion/analyzer.py
simcombustion/data/91sp_991re.yaml
simcombustion-0.2.0.dist-info/licenses/LICENSE
simcombustion-0.2.0.dist-info/METADATA
simcombustion-0.2.0.dist-info/WHEEL
simcombustion-0.2.0.dist-info/top_level.txt
simcombustion-0.2.0.dist-info/RECORD
