Metadata-Version: 2.4
Name: simcombustion
Version: 0.2.0
Summary: Una librería para análisis de combustión con Cantera.
Author-email: Nicolás Herrera Fernández <ni.herrefer@gmail.com>
Classifier: Programming Language :: Python :: 3
Classifier: License :: OSI Approved :: MIT License
Classifier: Operating System :: OS Independent
Classifier: Intended Audience :: Science/Research
Classifier: Topic :: Scientific/Engineering :: Chemistry
Requires-Python: >=3.8
License-File: LICENSE
Requires-Dist: numpy
Requires-Dist: cantera>=3.1.0
Dynamic: license-file
